pyaud_plugins/__init__.py
pyaud_plugins/_environ.py
pyaud_plugins/_parsers.py
pyaud_plugins/_plugins/__init__.py
pyaud_plugins/_plugins/action.py
pyaud_plugins/_plugins/audit.py
pyaud_plugins/_plugins/fix.py
pyaud_plugins/_plugins/parametrize.py
pyaud_plugins/_plugins/write.py
pyaud_plugins/_utils.py
pyaud_plugins/_version.py
pyaud_plugins/py.typed
pyaud_plugins-0.22.0.dist-info/LICENSE
pyaud_plugins-0.22.0.dist-info/METADATA
pyaud_plugins-0.22.0.dist-info/WHEEL
pyaud_plugins-0.22.0.dist-info/RECORD
