Metadata-Version: 2.1
Name: pyaud-plugins
Version: 0.22.0
Summary: Plugin package for Pyaud
Home-page: https://pypi.org/project/pyaud-plugins/
License: MIT
Keywords: audit,ci,plugins,pyaud,python
Author: jshwi
Author-email: stephen@jshwisolutions.com
Maintainer: jshwi
Maintainer-email: stephen@jshwisolutions.com
Requires-Python: >=3.8,<4.0
Classifier: License :: OSI Approved :: MIT License
Classifier: Programming Language :: Python :: 3
Classifier: Programming Language :: Python :: 3.8
Classifier: Programming Language :: Python :: 3.9
Classifier: Programming Language :: Python :: 3.10
Classifier: Programming Language :: Python :: 3.11
Classifier: Programming Language :: Python :: 3.12
Requires-Dist: Sphinx (>=4.3.2,<8.0.0)
Requires-Dist: black (>=24.1.1,<25.0)
Requires-Dist: constcheck (>=0,<1)
Requires-Dist: coverage (>=6.2,<8.0)
Requires-Dist: docformatter (==1.7.5)
Requires-Dist: docsig (>=0.34.0)
Requires-Dist: environs (>=9.4,<11.0)
Requires-Dist: flynt (>=0.75,<1.1)
Requires-Dist: gitpython (>=3.1.30,<4.0.0)
Requires-Dist: isort (>=5.10.1,<6.0.0)
Requires-Dist: mypy (>=0.930,<1.9)
Requires-Dist: pyaud (>=7.3.1)
Requires-Dist: pygments (>=2.16.1,<3.0.0)
Requires-Dist: pylint (>=2.12.2,<4.0.0)
Requires-Dist: pytest (>=7.2,<9.0)
Requires-Dist: pytest-cov (>=3,<5)
Requires-Dist: pyyaml (>=6.0,<7.0)
Requires-Dist: rich (>=13.5.2,<14.0.0)
Requires-Dist: setuptools (>=67.2,<70.0)
Requires-Dist: sphinx-markdown-builder (>=0.5.5,<0.6.0)
Requires-Dist: sphinxcontrib-fulltoc (>=1.2.0,<2.0.0)
Requires-Dist: sphinxcontrib-programoutput (>=0.17,<0.18)
Requires-Dist: toml-sort (>=0.20,<0.24)
Requires-Dist: tomli (>=2.0.1,<3.0.0)
Requires-Dist: vulture (>=2.3,<3.0)
Project-URL: Documentation, https://pyaud-plugins.readthedocs.io/en/latest
Project-URL: Repository, https://github.com/jshwi/pyaud-plugins
